pandabase/__init__.py
pandabase/companda.py
pandabase/helpers.py
pandabase/sql.py
pandabase/util.py
pandabase-0.5.0.dist-info/LICENSE
pandabase-0.5.0.dist-info/METADATA
pandabase-0.5.0.dist-info/WHEEL
pandabase-0.5.0.dist-info/top_level.txt
pandabase-0.5.0.dist-info/RECORD
