Metadata-Version: 2.1
Name: pandabase
Version: 0.5.0
Summary: pandabase links pandas DataFrames to SQL databases. Upsert, append, read, drop, describe...
Home-page: https://github.com/notsambeck/pandabase
Author: Sam Beck
Author-email: notsambeck@gmail.com
License: UNKNOWN
Platform: UNKNOWN
Classifier: Programming Language :: Python :: 3
Classifier: License :: OSI Approved :: MIT License
Classifier: Operating System :: OS Independent
Requires-Python: >=3.6
Requires-Dist: pandas (>=0.24.0)
Requires-Dist: sqlalchemy (>=1.3.0)
